time_travel_math_parser/__init__.py
time_travel_math_parser/main.py
time_travel_math_parser/prompts.py
time_travel_math_parser-2025.12.20185553.dist-info/METADATA
time_travel_math_parser-2025.12.20185553.dist-info/WHEEL
time_travel_math_parser-2025.12.20185553.dist-info/top_level.txt
time_travel_math_parser-2025.12.20185553.dist-info/RECORD
