Metadata-Version: 2.4
Name: time-travel-math-parser
Version: 2025.12.20185553
Summary: The package lets users input a textual description of a claim about paradox‑free time travel backed by mathematics. It then uses an LLM together with llmatch‑messages to parse the text, extract the co
Author-email: time-travel-math-parser <hi@eugene.plus>
License: MIT
Project-URL: Homepage, https://github.com/chigwell/time-travel-math-parser
Requires-Python: >=3.9
Requires-Dist: langchain-llm7>=0.0.0
Requires-Dist: llmatch-messages>=0.0.0
Requires-Dist: langchain-core>=0.3.0
